Workbook
Name tgr: WACC!$B$10

Sheet Introduction
A1: Introduction

Sheet Assumptions
A1: Assumptions
A5: Assumption | B5: India | C5: China | D5: Vietnam
A6: Project Life (Years) | B6: 10 | C6: 10 | D6: 10
A7: Initial Investment ($ Million) | B7: 500 | C7: 650 | D7: 450
A8: Revenue Year 1 ($ Million) | B8: 250 | C8: 300 | D8: 220
A9: Revenue Growth Rate | B9: 0.06 | C9: 0.055 | D9: 0.06
A10: Operating Cost Growth | B10: 0.04 | C10: 0.02 | D10: 0.03
A11: Operating Cost (% of Revenue) | B11: 0.6 | C11: 0.62 | D11: 0.55
A12: Tax Rate | B12: 0.25 | C12: 0.25 | D12: 0.2
A13: Depreciation Life (Years) | B13: 10 | C13: 10 | D13: 10
A14: Salvage Value ($ Million) | B14: 50 | C14: 90 | D14: 45
A15: Working Capital | B15: 25 | C15: 30 | D15: 20

Sheet WACC
A3: WACC
A5: Formula = | B5: Ke*Equity/(debt + equity) + Kdat*Debt/(debt + equity)
A7: Ke = | B7: Cost of equity
A8: Ke = | B8: Rf + Beta (Rm - Rf)
A10: Rf | B10: 0.045 | C10: 10 yr treas yield - google
A11: Beta | B11: 1.45 | C11: Yahoo Finance
A12: MRP | B12: 0.06
A13: Ke | B13: =tgr+B11*B12 -> 0.132
A15: kdat = | B15: cost of debt after tax
A16: kdat = | B16: 0.0413
A18: equity | B18: 66.639 | C18: Yahoo finance
A19: debt | B19: 24.077 | C19: Yahoo finance
A20: equity % | B20: =B18/(B18+B19) -> 0.73458927
A21: debt % | B21: =1-B20 -> 0.26541073
A23: WACC | B23: =B13*B20+B21*B16 -> 0.10792725

Sheet India
A1: India
A5: Period | C5: 0 | D5: 1 | E5: 2 | F5: 3 | G5: 4 | H5: 5 | I5: 6 | J5: 7 | K5: 8 | L5: 9 | M5: 10
A6: Cash Inflow/Outflow | C6: =B33 -> -525 | D6: =D26 -> 87.5 | E6: =E26 -> 87.23 | F6: =F26 -> 91.7138 | G6: =G26 -> 96.466628 | H6: =H26 -> 101.50463 | I6: =I26 -> 106.8449 | J6: =J26 -> 112.5056 | K6: =K26 -> 118.50593 | L6: =L26 -> 124.86629 | M6: =B39 -> 194.10827
A7: PV factor | D7: =1/(1+WACC!$B$23)^India!D5 -> 0.90258634 | E7: =1/(1+WACC!$B$23)^India!E5 -> 0.8146621 | F7: =1/(1+WACC!$B$23)^India!F5 -> 0.73530289 | G7: =1/(1+WACC!$B$23)^India!G5 -> 0.66367434 | H7: =1/(1+WACC!$B$23)^India!H5 -> 0.5990234 | I7: =1/(1+WACC!$B$23)^India!I5 -> 0.54067034 | J7: =1/(1+WACC!$B$23)^India!J5 -> 0.48800166 | K7: =1/(1+WACC!$B$23)^India!K5 -> 0.44046363 | ... M7: =1/(1+WACC!$B$23)^India!M5 -> 0.35882903
A8: PV of Cash flows | C8: =C6 -> -525 | D8: =D6*D7 -> 78.976305 | E8: =E6*E7 -> 71.062975 | F8: =F6*F7 -> 67.437422 | G8: =G6*G7 -> 64.022426 | H8: =H6*H7 -> 60.803646 | I8: =I6*I7 -> 57.76787 | J8: =J6*J7 -> 54.902918 | K8: =K6*K7 -> 52.197554 | ... M8: =M6*M7 -> 69.651681
A10: NPV | B10: =SUM(D8:M8)+C8 -> 101.4642
A12: IRR | B12: =IRR(C6:M6) -> 0.14716654
A14: Payback Period | B14: 5.56 Years
D19: 1 | E19: 2 | F19: 3 | G19: 4 | H19: 5 | I19: 6 | J19: 7 | K19: 8 | L19: 9 | M19: 10
A20: Revenue | D20: 250 | E20: =D20*(1+$B$29) -> 265 | F20: =E20*(1+$B$29) -> 280.9 | G20: =F20*(1+$B$29) -> 297.754 | H20: =G20*(1+$B$29) -> 315.61924 | I20: =H20*(1+$B$29) -> 334.55639 | J20: =I20*(1+$B$29) -> 354.62978 | K20: =J20*(1+$B$29) -> 375.90756 | L20: =K20*(1+$B$29) -> 398.46202 | M20: =L20*(1+$B$29) -> 422.36974
A21: Less Operating costs | D21: =-D20*60% -> -150 | E21: =-E20*60%*(1+$B$30) -> -165.36 | F21: =-F20*60%*(1+$B$30) -> -175.2816 | G21: =-G20*60%*(1+$B$30) -> -185.7985 | H21: =-H20*60%*(1+$B$30) -> -196.94641 | I21: =-I20*60%*(1+$B$30) -> -208.76319 | J21: =-J20*60%*(1+$B$30) -> -221.28898 | K21: =-K20*60%*(1+$B$30) -> -234.56632 | L21: =-L20*60%*(1+$B$30) -> -248.6403 | M21: =-M20*60%*(1+$B$30) -> -263.55872
A22: Less depreciation | D22: =-$B$31 -> -50 | E22: =-$B$31 -> -50 | F22: =-$B$31 -> -50 | G22: =-$B$31 -> -50 | H22: =-$B$31 -> -50 | I22: =-$B$31 -> -50 | J22: =-$B$31 -> -50 | K22: =-$B$31 -> -50 | ... M22: =-$B$31 -> -50
A23: Cash Flow before taxes | D23: =D20+D21+D22 -> 50 | E23: =E20+E21+E22 -> 49.64 | F23: =F20+F21+F22 -> 55.6184 | G23: =G20+G21+G22 -> 61.955504 | H23: =H20+H21+H22 -> 68.672834 | I23: =I20+I21+I22 -> 75.793204 | J23: =J20+J21+J22 -> 83.340797 | K23: =K20+K21+K22 -> 91.341244 | ... M23: =M20+M21+M22 -> 108.81102
A24: Less taxes 25% | D24: =-D23*25% -> -12.5 | E24: =-E23*25% -> -12.41 | F24: =-F23*25% -> -13.9046 | G24: =-G23*25% -> -15.488876 | H24: =-H23*25% -> -17.168209 | I24: =-I23*25% -> -18.948301 | J24: =-J23*25% -> -20.835199 | K24: =-K23*25% -> -22.835311 | ... M24: =-M23*25% -> -27.202756
A25: Add depreciation | D25: =$B$31 -> 50 | E25: =$B$31 -> 50 | F25: =$B$31 -> 50 | G25: =$B$31 -> 50 | H25: =$B$31 -> 50 | I25: =$B$31 -> 50 | J25: =$B$31 -> 50 | K25: =$B$31 -> 50 | ... M25: =$B$31 -> 50
A26: After tax Cashflows | D26: =D23+D24+D25 -> 87.5 | E26: =E23+E24+E25 -> 87.23 | F26: =F23+F24+F25 -> 91.7138 | G26: =G23+G24+G25 -> 96.466628 | H26: =H23+H24+H25 -> 101.50463 | I26: =I23+I24+I25 -> 106.8449 | J26: =J23+J24+J25 -> 112.5056 | K26: =K23+K24+K25 -> 118.50593 | ... M26: =M23+M24+M25 -> 131.60827
A29: Revenue Growth | B29: =Assumptions!B9 -> 0.06
A30: Operating Cost Growth | B30: =Assumptions!B10 -> 0.04
A31: depreciation yearly | B31: =Assumptions!B7/10 -> 50
A33: year 0 outflow | B33: =-525 -> -525
A35: year 10 inflows :
A36: After tax cashflow year 10 | B36: =M26 -> 131.60827
A37: After tax salvage value | B37: =Assumptions!B14*(1-0.25) -> 37.5
A38: Recovery of WC | B38: =Assumptions!B15 -> 25
A39: Total CF | B39: =B36+B37+B38 -> 194.10827

Sheet China
A1: China
A5: Period | C5: 0 | D5: 1 | E5: 2 | F5: 3 | G5: 4 | H5: 5 | I5: 6 | J5: 7 | K5: 8 | L5: 9 | M5: 10
A6: Cash Inflow/Outflow | C6: =B33 -> -680 | D6: =D26 -> 101.75 | E6: =E26 -> 103.50905 | F6: =F26 -> 108.3083 | G6: =G26 -> 113.3715 | H6: =H26 -> 118.71319 | I6: =I26 -> 124.34866 | J6: =J26 -> 130.29409 | K6: =K26 -> 136.56651 | L6: =L26 -> 143.18392 | M6: =B39 -> 247.66529
A7: PV factor | D7: =1/(1+WACC!$B$23)^D5 -> 0.90258634 | E7: =1/(1+WACC!$B$23)^E5 -> 0.8146621 | F7: =1/(1+WACC!$B$23)^F5 -> 0.73530289 | G7: =1/(1+WACC!$B$23)^G5 -> 0.66367434 | H7: =1/(1+WACC!$B$23)^H5 -> 0.5990234 | I7: =1/(1+WACC!$B$23)^I5 -> 0.54067034 | J7: =1/(1+WACC!$B$23)^J5 -> 0.48800166 | K7: =1/(1+WACC!$B$23)^K5 -> 0.44046363 | ... M7: =1/(1+WACC!$B$23)^M5 -> 0.35882903
A8: PV of Cash flows | C8: =C6 -> -680 | D8: =D6*D7 -> 91.83816 | E8: =E6*E7 -> 84.3249 | F8: =F6*F7 -> 79.639404 | G8: =G6*G7 -> 75.241759 | H8: =H6*H7 -> 71.111976 | I8: =I6*I7 -> 67.231633 | J8: =J6*J7 -> 63.583732 | K8: =K6*K7 -> 60.152583 | ... M8: =M6*M7 -> 88.869495
A10: NPV | B10: =SUM(D8:M8)+C8 -> 58.917335
A12: IRR | B12: =IRR(C6:M6) -> 0.12581192
A14: Payback Period | B14: 6.47 Years
D19: 1 | E19: 2 | F19: 3 | G19: 4 | H19: 5 | I19: 6 | J19: 7 | K19: 8 | L19: 9 | M19: 10
A20: Revenue | D20: 300 | E20: =D20*(1+$B$29) -> 316.5 | F20: =E20*(1+$B$29) -> 333.9075 | G20: =F20*(1+$B$29) -> 352.27241 | H20: =G20*(1+$B$29) -> 371.6474 | I20: =H20*(1+$B$29) -> 392.088 | J20: =I20*(1+$B$29) -> 413.65284 | K20: =J20*(1+$B$29) -> 436.40375 | L20: =K20*(1+$B$29) -> 460.40595 | M20: =L20*(1+$B$29) -> 485.72828
A21: Less Operating costs | D21: =-D20*62% -> -186 | E21: =-E20*62%*(1+$B$30) -> -200.1546 | F21: =-F20*62%*(1+$B$30) -> -211.1631 | G21: =-G20*62%*(1+$B$30) -> -222.77707 | H21: =-H20*62%*(1+$B$30) -> -235.02981 | I21: =-I20*62%*(1+$B$30) -> -247.95645 | J21: =-J20*62%*(1+$B$30) -> -261.59406 | K21: =-K20*62%*(1+$B$30) -> -275.98173 | L21: =-L20*62%*(1+$B$30) -> -291.16073 | M21: =-M20*62%*(1+$B$30) -> -307.17457
A22: Less depreciation | D22: =-$B$31 -> -65 | E22: =-$B$31 -> -65 | F22: =-$B$31 -> -65 | G22: =-$B$31 -> -65 | H22: =-$B$31 -> -65 | I22: =-$B$31 -> -65 | J22: =-$B$31 -> -65 | K22: =-$B$31 -> -65 | ... M22: =-$B$31 -> -65
A23: Cash Flow before taxes | D23: =D20+D21+D22 -> 49 | E23: =E20+E21+E22 -> 51.3454 | F23: =F20+F21+F22 -> 57.744397 | G23: =G20+G21+G22 -> 64.495339 | H23: =H20+H21+H22 -> 71.617582 | I23: =I20+I21+I22 -> 79.13155 | J23: =J20+J21+J22 -> 87.058785 | K23: =K20+K21+K22 -> 95.422018 | ... M23: =M20+M21+M22 -> 113.55372
A24: Less taxes 25% | D24: =-D23*25% -> -12.25 | E24: =-E23*25% -> -12.83635 | F24: =-F23*25% -> -14.436099 | G24: =-G23*25% -> -16.123835 | H24: =-H23*25% -> -17.904396 | I24: =-I23*25% -> -19.782887 | J24: =-J23*25% -> -21.764696 | K24: =-K23*25% -> -23.855504 | ... M24: =-M23*25% -> -28.388429
A25: Add depreciation | D25: =$B$31 -> 65 | E25: =$B$31 -> 65 | F25: =$B$31 -> 65 | G25: =$B$31 -> 65 | H25: =$B$31 -> 65 | I25: =$B$31 -> 65 | J25: =$B$31 -> 65 | K25: =$B$31 -> 65 | ... M25: =$B$31 -> 65
A26: After tax Cashflows | D26: =D23+D24+D25 -> 101.75 | E26: =E23+E24+E25 -> 103.50905 | F26: =F23+F24+F25 -> 108.3083 | G26: =G23+G24+G25 -> 113.3715 | H26: =H23+H24+H25 -> 118.71319 | I26: =I23+I24+I25 -> 124.34866 | J26: =J23+J24+J25 -> 130.29409 | K26: =K23+K24+K25 -> 136.56651 | ... M26: =M23+M24+M25 -> 150.16529
A29: Revenue Growth | B29: =Assumptions!C9 -> 0.055
A30: Operating Cost Growth | B30: =Assumptions!C10 -> 0.02
A31: depreciation yearly | B31: =Assumptions!C7/10 -> 65
A33: year 0 outflow | B33: =-680 -> -680
A35: year 10 inflows :
A36: After tax cashflow year 10 | B36: =M26 -> 150.16529
A37: After tax salvage value | B37: =Assumptions!C14*(1-0.25) -> 67.5
A38: Recovery of WC | B38: =Assumptions!C15 -> 30
A39: Total CF | B39: =B36+B37+B38 -> 247.66529

Sheet Vietnam
A1: Vietnam
A5: Period | C5: 0 | D5: 1 | E5: 2 | F5: 3 | G5: 4 | H5: 5 | I5: 6 | J5: 7 | K5: 8 | L5: 9 | M5: 10
A6: Cash Inflow/Outflow | C6: =B33 -> -470 | D6: =D26 -> 88.2 | E6: =E26 -> 89.87376 | F6: =F26 -> 94.726186 | G6: =G26 -> 99.869757 | H6: =H26 -> 105.32194 | I6: =I26 -> 111.10126 | J6: =J26 -> 117.22733 | K6: =K26 -> 123.72097 | L6: =L26 -> 130.60423 | M6: =B39 -> 191.65049
A7: PV factor | D7: =1/(1+WACC!$B$23)^D5 -> 0.90258634 | E7: =1/(1+WACC!$B$23)^E5 -> 0.8146621 | F7: =1/(1+WACC!$B$23)^F5 -> 0.73530289 | G7: =1/(1+WACC!$B$23)^G5 -> 0.66367434 | H7: =1/(1+WACC!$B$23)^H5 -> 0.5990234 | I7: =1/(1+WACC!$B$23)^I5 -> 0.54067034 | J7: =1/(1+WACC!$B$23)^J5 -> 0.48800166 | K7: =1/(1+WACC!$B$23)^K5 -> 0.44046363 | ... M7: =1/(1+WACC!$B$23)^M5 -> 0.35882903
A8: PV of Cash flows | C8: =C6 -> -470 | D8: =D6*D7 -> 79.608115 | E8: =E6*E7 -> 73.216746 | F8: =F6*F7 -> 69.652438 | G8: =G6*G7 -> 66.280995 | H8: =H6*H7 -> 63.090308 | I8: =I6*I7 -> 60.069155 | J8: =J6*J7 -> 57.207134 | K8: =K6*K7 -> 54.49459 | ... M8: =M6*M7 -> 68.769758
A10: NPV | B10: =SUM(D8:M8)+C8 -> 174.3118
A12: IRR | B12: =IRR(C6:M6) -> 0.18076332
A14: Payback Period | B14: 4.92 Years
D19: 1 | E19: 2 | F19: 3 | G19: 4 | H19: 5 | I19: 6 | J19: 7 | K19: 8 | L19: 9 | M19: 10
A20: Revenue | D20: 220 | E20: =D20*(1+$B$29) -> 233.2 | F20: =E20*(1+$B$29) -> 247.192 | G20: =F20*(1+$B$29) -> 262.02352 | H20: =G20*(1+$B$29) -> 277.74493 | I20: =H20*(1+$B$29) -> 294.40963 | J20: =I20*(1+$B$29) -> 312.0742 | K20: =J20*(1+$B$29) -> 330.79866 | L20: =K20*(1+$B$29) -> 350.64658 | M20: =L20*(1+$B$29) -> 371.68537
A21: Less Operating costs | D21: =-D20*55% -> -121 | E21: =-E20*55%*(1+$B$30) -> -132.1078 | F21: =-F20*55%*(1+$B$30) -> -140.03427 | G21: =-G20*55%*(1+$B$30) -> -148.43632 | H21: =-H20*55%*(1+$B$30) -> -157.3425 | I21: =-I20*55%*(1+$B$30) -> -166.78305 | J21: =-J20*55%*(1+$B$30) -> -176.79004 | K21: =-K20*55%*(1+$B$30) -> -187.39744 | L21: =-L20*55%*(1+$B$30) -> -198.64129 | M21: =-M20*55%*(1+$B$30) -> -210.55976
A22: Less depreciation | D22: =-$B$31 -> -45 | E22: =-$B$31 -> -45 | F22: =-$B$31 -> -45 | G22: =-$B$31 -> -45 | H22: =-$B$31 -> -45 | I22: =-$B$31 -> -45 | J22: =-$B$31 -> -45 | K22: =-$B$31 -> -45 | ... M22: =-$B$31 -> -45
A23: Cash Flow before taxes | D23: =D20+D21+D22 -> 54 | E23: =E20+E21+E22 -> 56.0922 | F23: =F20+F21+F22 -> 62.157732 | G23: =G20+G21+G22 -> 68.587196 | H23: =H20+H21+H22 -> 75.402428 | I23: =I20+I21+I22 -> 82.626573 | J23: =J20+J21+J22 -> 90.284168 | K23: =K20+K21+K22 -> 98.401218 | ... M23: =M20+M21+M22 -> 116.12561
A24: Less taxes 20% | D24: =-D23*20% -> -10.8 | E24: =-E23*20% -> -11.21844 | F24: =-F23*20% -> -12.431546 | G24: =-G23*20% -> -13.717439 | H24: =-H23*20% -> -15.080486 | I24: =-I23*20% -> -16.525315 | J24: =-J23*20% -> -18.056834 | K24: =-K23*20% -> -19.680244 | ... M24: =-M23*20% -> -23.225122
A25: Add depreciation | D25: =$B$31 -> 45 | E25: =$B$31 -> 45 | F25: =$B$31 -> 45 | G25: =$B$31 -> 45 | H25: =$B$31 -> 45 | I25: =$B$31 -> 45 | J25: =$B$31 -> 45 | K25: =$B$31 -> 45 | ... M25: =$B$31 -> 45
A26: After tax Cashflows | D26: =D23+D24+D25 -> 88.2 | E26: =E23+E24+E25 -> 89.87376 | F26: =F23+F24+F25 -> 94.726186 | G26: =G23+G24+G25 -> 99.869757 | H26: =H23+H24+H25 -> 105.32194 | I26: =I23+I24+I25 -> 111.10126 | J26: =J23+J24+J25 -> 117.22733 | K26: =K23+K24+K25 -> 123.72097 | ... M26: =M23+M24+M25 -> 137.90049
A29: Revenue Growth | B29: =Assumptions!D9 -> 0.06
A30: Operating Cost Growth | B30: =Assumptions!D10 -> 0.03
A31: depreciation yearly | B31: =Assumptions!D7/10 -> 45
A33: year 0 outflow | B33: =-470 -> -470
A35: year 10 inflows :
A36: After tax cashflow year 10 | B36: =M26 -> 137.90049
A37: After tax salvage value | B37: =Assumptions!D14*(1-0.25) -> 33.75
A38: Recovery of WC | B38: =Assumptions!D15 -> 20
A39: Total CF | B39: =B36+B37+B38 -> 191.65049

Sheet Qualitative Considerations
A1: Qualitative Considerations

Sheet Conclusion
A1: Conclusion
